parse_ebnf/__about__.py
parse_ebnf/__init__.py
parse_ebnf/nodes.py
parse_ebnf/parsing.py
parse_ebnf-2.0.2.dist-info/METADATA
parse_ebnf-2.0.2.dist-info/WHEEL
parse_ebnf-2.0.2.dist-info/licenses/LICENSE
parse_ebnf-2.0.2.dist-info/RECORD
