Metadata-Version: 2.3
Name: parse-ebnf
Version: 2.0.2
Summary: A parse tree generator for extended Backus-Naur form.
Project-URL: Documentation, https://github.com/ChaosInventor/parse-ebnf#readme
Project-URL: Issues, https://github.com/ChaosInventor/parse-ebnf/issues
Project-URL: Source, https://github.com/ChaosInventor/parse-ebnf
Author-email: ChaosInventor <chaosinventor@yandex.com>
License-Expression: MIT
License-File: LICENSE
Keywords: EBNF,Extended Backus-Naur Form,Parse tree,Parser
Classifier: Development Status :: 4 - Beta
Classifier: Programming Language :: Python
Classifier: Programming Language :: Python :: 3.7
Classifier: Programming Language :: Python :: 3.8
Classifier: Programming Language :: Python :: 3.9
Classifier: Programming Language :: Python :: 3.10
Classifier: Programming Language :: Python :: 3.11
Classifier: Programming Language :: Python :: Implementation :: CPython
Classifier: Programming Language :: Python :: Implementation :: PyPy
Requires-Python: >=3.7
